hackr/__init__.py
hackr/actions.py
hackr/generator.py
hackr/web.py
hackr-0.1.1.dist-info/DESCRIPTION.rst
hackr-0.1.1.dist-info/METADATA
hackr-0.1.1.dist-info/RECORD
hackr-0.1.1.dist-info/WHEEL
hackr-0.1.1.dist-info/metadata.json
hackr-0.1.1.dist-info/top_level.txt
