Metadata-Version: 2.0
Name: hackr
Version: 0.1.1
Summary: A unicorn for Hackathons
Home-page: https://github.com/pytorn/hackr
Author: Ashwini Purohit
Author-email: geek.ashwini@gmail.com
License: Apache 2.0
Platform: UNKNOWN
Classifier: Intended Audience :: Developers
Classifier: Topic :: Software Development :: Libraries
Classifier: Programming Language :: Python :: 2.7
Requires-Dist: Faker (==0.8.4)
Requires-Dist: requests (==2.18.4)
